README.rst
setup.py
django_table_renderers/__init__.py
django_table_renderers.egg-info/PKG-INFO
django_table_renderers.egg-info/SOURCES.txt
django_table_renderers.egg-info/dependency_links.txt
django_table_renderers.egg-info/top_level.txt